llama_index/multi_modal_llms/replicate_multi_modal/__init__.py
llama_index/multi_modal_llms/replicate_multi_modal/base.py
llama_index_multi_modal_llms_replicate_multi_modal-0.1.3.dist-info/METADATA
llama_index_multi_modal_llms_replicate_multi_modal-0.1.3.dist-info/WHEEL
llama_index_multi_modal_llms_replicate_multi_modal-0.1.3.dist-info/RECORD
