Metadata-Version: 2.1
Name: llama-index-multi-modal-llms-replicate-multi-modal
Version: 0.1.3
Summary: llama-index multi-modal-llms replicate multi modal integration
License: MIT
Author: Your Name
Author-email: you@example.com
Requires-Python: >=3.8.1,<4.0
Classifier: License :: OSI Approved :: MIT License
Classifier: Programming Language :: Python :: 3
Classifier: Programming Language :: Python :: 3.9
Classifier: Programming Language :: Python :: 3.10
Classifier: Programming Language :: Python :: 3.11
Classifier: Programming Language :: Python :: 3.12
Requires-Dist: llama-index-core (>=0.10.1,<0.11.0)
